{
  "name": "International Studies",
  "college": "College of Arts & Sciences",
  "dept": "multidisciplinary",
  "degree_type": "4 Year Plan",
  "degree_awarded": "BA",
  "notes": [
    {
      "note": "Keep in mind that minimum grades on road map are for individual coursework only.  Students must maintain a minimum of a 2.0 cumulative grade point average for admission to and graduation from the College of Arts and Sciences.  Minimums listed for the individual courses do NOT meet the cumulative minimum."
    },
    {
      "note": "INTS Thematic Concentrations are subject focused (see INTS handbook), INTS Areas are regionally focused (see INTS handbook), Minors should complement TCs for depth, INTS majors are prepared for entry level positions Advanced degrees needed for career jobs."
    }
  ],
  "terms": [
    {
      "term_items": [
        {
          "name": "POLS 240: International Politics",
          "crucial": false,
          "min_grade": "C",
          "credits": 3,
          "courses": [
            {
              "number": "POLS 240",
              "title": "International Politics"
            }
          ]
        },
        {
          "name": "ENGL 110: Accelerated Composition or ENGL 111: Composition I and ENGL 112: Composition II or ENGL 113: Enhanced Composition",
          "crucial": false,
          "min_grade": "C",
          "credits": 3,
          "courses": [

          ]
        },
        {
          "name": "Freshman Academic Choice",
          "crucial": false,
          "min_grade": "D-",
          "credits": 3,
          "courses": [

          ]
        },
        {
          "name": "MATH",
          "crucial": false,
          "min_grade": "C",
          "credits": 3,
          "courses": [

          ]
        },
        {
          "name": "Language 101",
          "crucial": false,
          "min_grade": "C",
          "credits": 3,
          "courses": [

          ]
        }
      ]
    },
    {
      "term_items": [
        {
          "name": "POLS 240: International Politics (If it was not taken the previous semester)",
          "crucial": false,
          "min_grade": "C",
          "credits": 3,
          "courses": [
            {
              "number": "POLS 240",
              "title": "International Politics"
            }
          ]
        },
        {
          "name": "ENGL 120: Composition III",
          "crucial": false,
          "min_grade": "C",
          "credits": 3,
          "courses": [

          ]
        },
        {
          "name": "Physical and Natural Science",
          "crucial": false,
          "min_grade": "C",
          "credits": 4,
          "courses": [

          ]
        },
        {
          "name": "Elective Any Level or Language 102",
          "crucial": false,
          "min_grade": "C",
          "credits": 3,
          "courses": [

          ]
        },
        {
          "name": "Minor or 2nd Major Requirement",
          "crucial": false,
          "min_grade": "C",
          "credits": 3,
          "courses": [

          ]
        }
      ]
    },
    {
      "term_items": [
        {
          "name": "Language 201",
          "crucial": false,
          "min_grade": "C",
          "credits": 3,
          "courses": [

          ]
        },
        {
          "name": "INTS HUM or SOCSCI for TC",
          "crucial": false,
          "min_grade": "C",
          "credits": 3,
          "courses": [

          ]
        },
        {
          "name": "Minor or 2nd Major Requirement",
          "crucial": false,
          "min_grade": "C",
          "credits": 3,
          "courses": [

          ]
        },
        {
          "name": "CJ 130 or PHIL 156 or ENGL 219 or ENGL 220",
          "crucial": false,
          "min_grade": "C",
          "credits": 3,
          "courses": [
            {
              "number": "ENGL 219",
              "title": "Tech & Professional Writing"
            },
            {
              "number": "ENGL 220",
              "title": "Expository Writing"
            },
            {
              "number": "CJ 130",
              "title": "Public Speaking"
            },
            {
              "number": "PHIL 156",
              "title": "Reasoning & Critical Thinking"
            }
          ]
        },
        {
          "name": "Social Behavioral Science",
          "crucial": false,
          "min_grade": "C",
          "credits": 3,
          "courses": [

          ]
        }
      ]
    },
    {
      "term_items": [
        {
          "name": "Language 202",
          "crucial": false,
          "min_grade": "C",
          "credits": 3,
          "courses": [

          ]
        },
        {
          "name": "INTS HUM or SOCSCI for TC",
          "crucial": false,
          "min_grade": "C",
          "credits": 3,
          "courses": [

          ]
        },
        {
          "name": "INTS Area or 1st TC 300+ level course",
          "crucial": false,
          "min_grade": "C",
          "credits": 3,
          "courses": [

          ]
        },
        {
          "name": "Minor or 2nd Major Requirement",
          "crucial": false,
          "min_grade": "C",
          "credits": 3,
          "courses": [

          ]
        },
        {
          "name": "Humanities",
          "crucial": false,
          "min_grade": "C",
          "credits": 3,
          "courses": [

          ]
        }
      ]
    },
    {
      "term_items": [
        {
          "name": "INTS AREA 1st or 2nd",
          "crucial": false,
          "min_grade": "C",
          "credits": 3,
          "courses": [

          ]
        },
        {
          "name": "INTS TC 1st or 2nd",
          "crucial": false,
          "min_grade": "C",
          "credits": 3,
          "courses": [

          ]
        },
        {
          "name": "Social Behavioral Science",
          "crucial": false,
          "min_grade": "C",
          "credits": 3,
          "courses": [

          ]
        },
        {
          "name": "Fine Arts",
          "crucial": false,
          "min_grade": "C",
          "credits": 3,
          "courses": [

          ]
        },
        {
          "name": "Minor or 2nd Major Requirement",
          "crucial": false,
          "min_grade": "C",
          "credits": 3,
          "courses": [

          ]
        }
      ]
    },
    {
      "term_items": [
        {
          "name": "INTS AREA 2nd or 3rd",
          "crucial": false,
          "min_grade": "C",
          "credits": 3,
          "courses": [

          ]
        },
        {
          "name": "INTS TC 2nd or 3rd",
          "crucial": false,
          "min_grade": "C",
          "credits": 3,
          "courses": [

          ]
        },
        {
          "name": "Humanities",
          "crucial": false,
          "min_grade": "D-",
          "credits": 3,
          "courses": [

          ]
        },
        {
          "name": "Physical and Natural Science",
          "crucial": false,
          "min_grade": "C",
          "credits": 3,
          "courses": [

          ]
        },
        {
          "name": "Minor or 2nd Major Requirement",
          "crucial": false,
          "min_grade": "C",
          "credits": 3,
          "courses": [

          ]
        }
      ]
    },
    {
      "term_items": [
        {
          "name": "INTS 400 or INTS AREA/TC 3rd",
          "crucial": false,
          "min_grade": "C",
          "credits": 3,
          "courses": [

          ]
        },
        {
          "name": "Minor or 2nd Major Requirement",
          "crucial": false,
          "min_grade": "C",
          "credits": 3,
          "courses": [

          ]
        },
        {
          "name": "2nd Major or Upper Division Elective",
          "crucial": false,
          "min_grade": "C",
          "credits": 9,
          "courses": [

          ]
        }
      ]
    },
    {
      "term_items": [
        {
          "name": "INTS 400: Directed Study and Travel Abroad",
          "crucial": false,
          "min_grade": "C",
          "credits": 3,
          "courses": [
            {
              "number": "INTS 400",
              "title": "Study Abroad"
            }
          ]
        },
        {
          "name": "2nd Major or Upper Division Elective",
          "crucial": false,
          "min_grade": "C",
          "credits": 12,
          "courses": [

          ]
        }
      ]
    }
  ]
}
